<stg><name>entry_proc</name>


<trans_list>
</trans_list>



<state_list>

<state id="1" st_id="1">

<operation id="2" st_id="1" stage="1" lat="1">
<core>NULL</core>
<MemPortIdVec></MemPortIdVec>
<condition id="-1">
<or_exp><and_exp></and_exp></or_exp>
</condition>

<Node id="9" bw="0" op_0_bw="0" op_1_bw="32" op_2_bw="0" op_3_bw="32" op_4_bw="32" op_5_bw="0" op_6_bw="32" op_7_bw="32" op_8_bw="0" op_9_bw="0" op_10_bw="0" op_11_bw="32" op_12_bw="32" op_13_bw="32" op_14_bw="32" op_15_bw="0" op_16_bw="0" op_17_bw="32" op_18_bw="32">
<![CDATA[
entry:0 %specinterface_ln0 = specinterface void @_ssdm_op_SpecInterface, i32 %S_c61, void @ap_fifo_str, i32 0, i32 0, void @p_str, i32 0, i32 0, void @p_str, void @p_str, void @p_str, i32 2, i32 2, i32 16, i32 16, void @p_str, void @ScalarProp_str, i32 4294967295, i32 0

]]></Node>
<StgValue><ssdm name="specinterface_ln0"/></StgValue>
</operation>

<operation id="3" st_id="1" stage="1" lat="1">
<core>NULL</core>
<MemPortIdVec></MemPortIdVec>
<condition id="-1">
<or_exp><and_exp></and_exp></or_exp>
</condition>

<Node id="10" bw="32" op_0_bw="32" op_1_bw="32">
<![CDATA[
entry:1 %S_read = read i32 @_ssdm_op_Read.ap_auto.i32, i32 %S

]]></Node>
<StgValue><ssdm name="S_read"/></StgValue>
</operation>

<operation id="4" st_id="1" stage="1" lat="1">
<core>NULL</core>
<MemPortIdVec></MemPortIdVec>
<condition id="-1">
<or_exp><and_exp></and_exp></or_exp>
</condition>

<Node id="11" bw="32" op_0_bw="32" op_1_bw="32">
<![CDATA[
entry:2 %P_read = read i32 @_ssdm_op_Read.ap_auto.i32, i32 %P

]]></Node>
<StgValue><ssdm name="P_read"/></StgValue>
</operation>

<operation id="5" st_id="1" stage="1" lat="1">
<core>NULL</core>
<MemPortIdVec></MemPortIdVec>
<condition id="-1">
<or_exp><and_exp></and_exp></or_exp>
</condition>

<Node id="12" bw="32" op_0_bw="32" op_1_bw="32">
<![CDATA[
entry:3 %K_read = read i32 @_ssdm_op_Read.ap_auto.i32, i32 %K

]]></Node>
<StgValue><ssdm name="K_read"/></StgValue>
</operation>

<operation id="6" st_id="1" stage="1" lat="1">
<core>NULL</core>
<MemPortIdVec></MemPortIdVec>
<condition id="-1">
<or_exp><and_exp></and_exp></or_exp>
</condition>

<Node id="13" bw="64" op_0_bw="64" op_1_bw="64">
<![CDATA[
entry:4 %Output_r_read = read i64 @_ssdm_op_Read.ap_auto.i64, i64 %Output_r

]]></Node>
<StgValue><ssdm name="Output_r_read"/></StgValue>
</operation>

<operation id="7" st_id="1" stage="1" lat="1">
<core>FIFO_SRL</core>
<MemPortIdVec></MemPortIdVec>
<condition id="-1">
<or_exp><and_exp></and_exp></or_exp>
</condition>

<Node id="14" bw="0" op_0_bw="0" op_1_bw="32" op_2_bw="32">
<![CDATA[
entry:5 %write_ln0 = write void @_ssdm_op_Write.ap_fifo.i32P0A, i32 %S_c61, i32 %S_read

]]></Node>
<StgValue><ssdm name="write_ln0"/></StgValue>
</operation>

<operation id="8" st_id="1" stage="1" lat="1">
<core>NULL</core>
<MemPortIdVec></MemPortIdVec>
<condition id="-1">
<or_exp><and_exp></and_exp></or_exp>
</condition>

<Node id="15" bw="0" op_0_bw="0" op_1_bw="32" op_2_bw="0" op_3_bw="32" op_4_bw="32" op_5_bw="0" op_6_bw="32" op_7_bw="32" op_8_bw="0" op_9_bw="0" op_10_bw="0" op_11_bw="32" op_12_bw="32" op_13_bw="32" op_14_bw="32" op_15_bw="0" op_16_bw="0" op_17_bw="32" op_18_bw="32">
<![CDATA[
entry:6 %specinterface_ln0 = specinterface void @_ssdm_op_SpecInterface, i32 %P_c60, void @ap_fifo_str, i32 0, i32 0, void @p_str, i32 0, i32 0, void @p_str, void @p_str, void @p_str, i32 2, i32 2, i32 16, i32 16, void @p_str, void @ScalarProp_str, i32 4294967295, i32 0

]]></Node>
<StgValue><ssdm name="specinterface_ln0"/></StgValue>
</operation>

<operation id="9" st_id="1" stage="1" lat="1">
<core>FIFO_SRL</core>
<MemPortIdVec></MemPortIdVec>
<condition id="-1">
<or_exp><and_exp></and_exp></or_exp>
</condition>

<Node id="16" bw="0" op_0_bw="0" op_1_bw="32" op_2_bw="32">
<![CDATA[
entry:7 %write_ln0 = write void @_ssdm_op_Write.ap_fifo.i32P0A, i32 %P_c60, i32 %P_read

]]></Node>
<StgValue><ssdm name="write_ln0"/></StgValue>
</operation>

<operation id="10" st_id="1" stage="1" lat="1">
<core>NULL</core>
<MemPortIdVec></MemPortIdVec>
<condition id="-1">
<or_exp><and_exp></and_exp></or_exp>
</condition>

<Node id="17" bw="0" op_0_bw="0" op_1_bw="32" op_2_bw="0" op_3_bw="32" op_4_bw="32" op_5_bw="0" op_6_bw="32" op_7_bw="32" op_8_bw="0" op_9_bw="0" op_10_bw="0" op_11_bw="32" op_12_bw="32" op_13_bw="32" op_14_bw="32" op_15_bw="0" op_16_bw="0" op_17_bw="32" op_18_bw="32">
<![CDATA[
entry:8 %specinterface_ln0 = specinterface void @_ssdm_op_SpecInterface, i32 %K_c58, void @ap_fifo_str, i32 0, i32 0, void @p_str, i32 0, i32 0, void @p_str, void @p_str, void @p_str, i32 2, i32 2, i32 16, i32 16, void @p_str, void @ScalarProp_str, i32 4294967295, i32 0

]]></Node>
<StgValue><ssdm name="specinterface_ln0"/></StgValue>
</operation>

<operation id="11" st_id="1" stage="1" lat="1">
<core>FIFO_SRL</core>
<MemPortIdVec></MemPortIdVec>
<condition id="-1">
<or_exp><and_exp></and_exp></or_exp>
</condition>

<Node id="18" bw="0" op_0_bw="0" op_1_bw="32" op_2_bw="32">
<![CDATA[
entry:9 %write_ln0 = write void @_ssdm_op_Write.ap_fifo.i32P0A, i32 %K_c58, i32 %K_read

]]></Node>
<StgValue><ssdm name="write_ln0"/></StgValue>
</operation>

<operation id="12" st_id="1" stage="1" lat="1">
<core>NULL</core>
<MemPortIdVec></MemPortIdVec>
<condition id="-1">
<or_exp><and_exp></and_exp></or_exp>
</condition>

<Node id="19" bw="0" op_0_bw="0" op_1_bw="64" op_2_bw="0" op_3_bw="32" op_4_bw="32" op_5_bw="0" op_6_bw="32" op_7_bw="32" op_8_bw="0" op_9_bw="0" op_10_bw="0" op_11_bw="32" op_12_bw="32" op_13_bw="32" op_14_bw="32" op_15_bw="0" op_16_bw="0" op_17_bw="32" op_18_bw="32">
<![CDATA[
entry:10 %specinterface_ln0 = specinterface void @_ssdm_op_SpecInterface, i64 %Output_r_c, void @ap_fifo_str, i32 0, i32 0, void @p_str, i32 0, i32 0, void @p_str, void @p_str, void @p_str, i32 2, i32 2, i32 16, i32 16, void @p_str, void @ScalarProp_str, i32 4294967295, i32 0

]]></Node>
<StgValue><ssdm name="specinterface_ln0"/></StgValue>
</operation>

<operation id="13" st_id="1" stage="1" lat="1">
<core>FIFO_SRL</core>
<MemPortIdVec></MemPortIdVec>
<condition id="-1">
<or_exp><and_exp></and_exp></or_exp>
</condition>

<Node id="20" bw="0" op_0_bw="0" op_1_bw="64" op_2_bw="64">
<![CDATA[
entry:11 %write_ln0 = write void @_ssdm_op_Write.ap_fifo.i64P0A, i64 %Output_r_c, i64 %Output_r_read

]]></Node>
<StgValue><ssdm name="write_ln0"/></StgValue>
</operation>

<operation id="14" st_id="1" stage="1" lat="1">
<core>NULL</core>
<MemPortIdVec></MemPortIdVec>
<condition id="-1">
<or_exp><and_exp></and_exp></or_exp>
</condition>

<Node id="21" bw="0">
<![CDATA[
entry:12 %ret_ln0 = ret

]]></Node>
<StgValue><ssdm name="ret_ln0"/></StgValue>
</operation>
</state>
</state_list>


<ports>
<port id="15" name="Output_r" dir="0" iftype="0">
<core>NULL</core><StgValue><ssdm name="Output_r"/></StgValue>
</port>
<port id="16" name="Output_r_c" dir="1" iftype="3">
<core>FIFO_SRL</core><StgValue><ssdm name="Output_r_c"/></StgValue>
</port>
<port id="17" name="K" dir="0" iftype="0">
<core>NULL</core><StgValue><ssdm name="K"/></StgValue>
</port>
<port id="18" name="K_c58" dir="1" iftype="3">
<core>FIFO_SRL</core><StgValue><ssdm name="K_c58"/></StgValue>
</port>
<port id="19" name="P" dir="0" iftype="0">
<core>NULL</core><StgValue><ssdm name="P"/></StgValue>
</port>
<port id="20" name="P_c60" dir="1" iftype="3">
<core>FIFO_SRL</core><StgValue><ssdm name="P_c60"/></StgValue>
</port>
<port id="21" name="S" dir="0" iftype="0">
<core>NULL</core><StgValue><ssdm name="S"/></StgValue>
</port>
<port id="22" name="S_c61" dir="1" iftype="3">
<core>FIFO_SRL</core><StgValue><ssdm name="S_c61"/></StgValue>
</port>
</ports>


<dataflows>
<dataflow id="24" from="_ssdm_op_SpecInterface" to="specinterface_ln0" fromId="23" toId="2">
</dataflow>
<dataflow id="25" from="S_c61" to="specinterface_ln0" fromId="22" toId="2">
</dataflow>
<dataflow id="27" from="ap_fifo_str" to="specinterface_ln0" fromId="26" toId="2">
</dataflow>
<dataflow id="29" from="StgValue_28" to="specinterface_ln0" fromId="28" toId="2">
</dataflow>
<dataflow id="30" from="StgValue_28" to="specinterface_ln0" fromId="28" toId="2">
</dataflow>
<dataflow id="32" from="p_str" to="specinterface_ln0" fromId="31" toId="2">
</dataflow>
<dataflow id="33" from="StgValue_28" to="specinterface_ln0" fromId="28" toId="2">
</dataflow>
<dataflow id="34" from="StgValue_28" to="specinterface_ln0" fromId="28" toId="2">
</dataflow>
<dataflow id="35" from="p_str" to="specinterface_ln0" fromId="31" toId="2">
</dataflow>
<dataflow id="36" from="p_str" to="specinterface_ln0" fromId="31" toId="2">
</dataflow>
<dataflow id="37" from="p_str" to="specinterface_ln0" fromId="31" toId="2">
</dataflow>
<dataflow id="39" from="StgValue_38" to="specinterface_ln0" fromId="38" toId="2">
</dataflow>
<dataflow id="40" from="StgValue_38" to="specinterface_ln0" fromId="38" toId="2">
</dataflow>
<dataflow id="42" from="StgValue_41" to="specinterface_ln0" fromId="41" toId="2">
</dataflow>
<dataflow id="43" from="StgValue_41" to="specinterface_ln0" fromId="41" toId="2">
</dataflow>
<dataflow id="44" from="p_str" to="specinterface_ln0" fromId="31" toId="2">
</dataflow>
<dataflow id="46" from="ScalarProp_str" to="specinterface_ln0" fromId="45" toId="2">
</dataflow>
<dataflow id="48" from="StgValue_47" to="specinterface_ln0" fromId="47" toId="2">
</dataflow>
<dataflow id="49" from="StgValue_28" to="specinterface_ln0" fromId="28" toId="2">
</dataflow>
<dataflow id="51" from="_ssdm_op_Read.ap_auto.i32" to="S_read" fromId="50" toId="3">
</dataflow>
<dataflow id="52" from="S" to="S_read" fromId="21" toId="3">
</dataflow>
<dataflow id="53" from="_ssdm_op_Read.ap_auto.i32" to="P_read" fromId="50" toId="4">
</dataflow>
<dataflow id="54" from="P" to="P_read" fromId="19" toId="4">
</dataflow>
<dataflow id="55" from="_ssdm_op_Read.ap_auto.i32" to="K_read" fromId="50" toId="5">
</dataflow>
<dataflow id="56" from="K" to="K_read" fromId="17" toId="5">
</dataflow>
<dataflow id="58" from="_ssdm_op_Read.ap_auto.i64" to="Output_r_read" fromId="57" toId="6">
</dataflow>
<dataflow id="59" from="Output_r" to="Output_r_read" fromId="15" toId="6">
</dataflow>
<dataflow id="61" from="_ssdm_op_Write.ap_fifo.i32P0A" to="write_ln0" fromId="60" toId="7">
</dataflow>
<dataflow id="62" from="S_c61" to="write_ln0" fromId="22" toId="7">
</dataflow>
<dataflow id="63" from="S_read" to="write_ln0" fromId="3" toId="7">
</dataflow>
<dataflow id="64" from="_ssdm_op_SpecInterface" to="specinterface_ln0" fromId="23" toId="8">
</dataflow>
<dataflow id="65" from="P_c60" to="specinterface_ln0" fromId="20" toId="8">
</dataflow>
<dataflow id="66" from="ap_fifo_str" to="specinterface_ln0" fromId="26" toId="8">
</dataflow>
<dataflow id="67" from="StgValue_28" to="specinterface_ln0" fromId="28" toId="8">
</dataflow>
<dataflow id="68" from="StgValue_28" to="specinterface_ln0" fromId="28" toId="8">
</dataflow>
<dataflow id="69" from="p_str" to="specinterface_ln0" fromId="31" toId="8">
</dataflow>
<dataflow id="70" from="StgValue_28" to="specinterface_ln0" fromId="28" toId="8">
</dataflow>
<dataflow id="71" from="StgValue_28" to="specinterface_ln0" fromId="28" toId="8">
</dataflow>
<dataflow id="72" from="p_str" to="specinterface_ln0" fromId="31" toId="8">
</dataflow>
<dataflow id="73" from="p_str" to="specinterface_ln0" fromId="31" toId="8">
</dataflow>
<dataflow id="74" from="p_str" to="specinterface_ln0" fromId="31" toId="8">
</dataflow>
<dataflow id="75" from="StgValue_38" to="specinterface_ln0" fromId="38" toId="8">
</dataflow>
<dataflow id="76" from="StgValue_38" to="specinterface_ln0" fromId="38" toId="8">
</dataflow>
<dataflow id="77" from="StgValue_41" to="specinterface_ln0" fromId="41" toId="8">
</dataflow>
<dataflow id="78" from="StgValue_41" to="specinterface_ln0" fromId="41" toId="8">
</dataflow>
<dataflow id="79" from="p_str" to="specinterface_ln0" fromId="31" toId="8">
</dataflow>
<dataflow id="80" from="ScalarProp_str" to="specinterface_ln0" fromId="45" toId="8">
</dataflow>
<dataflow id="81" from="StgValue_47" to="specinterface_ln0" fromId="47" toId="8">
</dataflow>
<dataflow id="82" from="StgValue_28" to="specinterface_ln0" fromId="28" toId="8">
</dataflow>
<dataflow id="83" from="_ssdm_op_Write.ap_fifo.i32P0A" to="write_ln0" fromId="60" toId="9">
</dataflow>
<dataflow id="84" from="P_c60" to="write_ln0" fromId="20" toId="9">
</dataflow>
<dataflow id="85" from="P_read" to="write_ln0" fromId="4" toId="9">
</dataflow>
<dataflow id="86" from="_ssdm_op_SpecInterface" to="specinterface_ln0" fromId="23" toId="10">
</dataflow>
<dataflow id="87" from="K_c58" to="specinterface_ln0" fromId="18" toId="10">
</dataflow>
<dataflow id="88" from="ap_fifo_str" to="specinterface_ln0" fromId="26" toId="10">
</dataflow>
<dataflow id="89" from="StgValue_28" to="specinterface_ln0" fromId="28" toId="10">
</dataflow>
<dataflow id="90" from="StgValue_28" to="specinterface_ln0" fromId="28" toId="10">
</dataflow>
<dataflow id="91" from="p_str" to="specinterface_ln0" fromId="31" toId="10">
</dataflow>
<dataflow id="92" from="StgValue_28" to="specinterface_ln0" fromId="28" toId="10">
</dataflow>
<dataflow id="93" from="StgValue_28" to="specinterface_ln0" fromId="28" toId="10">
</dataflow>
<dataflow id="94" from="p_str" to="specinterface_ln0" fromId="31" toId="10">
</dataflow>
<dataflow id="95" from="p_str" to="specinterface_ln0" fromId="31" toId="10">
</dataflow>
<dataflow id="96" from="p_str" to="specinterface_ln0" fromId="31" toId="10">
</dataflow>
<dataflow id="97" from="StgValue_38" to="specinterface_ln0" fromId="38" toId="10">
</dataflow>
<dataflow id="98" from="StgValue_38" to="specinterface_ln0" fromId="38" toId="10">
</dataflow>
<dataflow id="99" from="StgValue_41" to="specinterface_ln0" fromId="41" toId="10">
</dataflow>
<dataflow id="100" from="StgValue_41" to="specinterface_ln0" fromId="41" toId="10">
</dataflow>
<dataflow id="101" from="p_str" to="specinterface_ln0" fromId="31" toId="10">
</dataflow>
<dataflow id="102" from="ScalarProp_str" to="specinterface_ln0" fromId="45" toId="10">
</dataflow>
<dataflow id="103" from="StgValue_47" to="specinterface_ln0" fromId="47" toId="10">
</dataflow>
<dataflow id="104" from="StgValue_28" to="specinterface_ln0" fromId="28" toId="10">
</dataflow>
<dataflow id="105" from="_ssdm_op_Write.ap_fifo.i32P0A" to="write_ln0" fromId="60" toId="11">
</dataflow>
<dataflow id="106" from="K_c58" to="write_ln0" fromId="18" toId="11">
</dataflow>
<dataflow id="107" from="K_read" to="write_ln0" fromId="5" toId="11">
</dataflow>
<dataflow id="108" from="_ssdm_op_SpecInterface" to="specinterface_ln0" fromId="23" toId="12">
</dataflow>
<dataflow id="109" from="Output_r_c" to="specinterface_ln0" fromId="16" toId="12">
</dataflow>
<dataflow id="110" from="ap_fifo_str" to="specinterface_ln0" fromId="26" toId="12">
</dataflow>
<dataflow id="111" from="StgValue_28" to="specinterface_ln0" fromId="28" toId="12">
</dataflow>
<dataflow id="112" from="StgValue_28" to="specinterface_ln0" fromId="28" toId="12">
</dataflow>
<dataflow id="113" from="p_str" to="specinterface_ln0" fromId="31" toId="12">
</dataflow>
<dataflow id="114" from="StgValue_28" to="specinterface_ln0" fromId="28" toId="12">
</dataflow>
<dataflow id="115" from="StgValue_28" to="specinterface_ln0" fromId="28" toId="12">
</dataflow>
<dataflow id="116" from="p_str" to="specinterface_ln0" fromId="31" toId="12">
</dataflow>
<dataflow id="117" from="p_str" to="specinterface_ln0" fromId="31" toId="12">
</dataflow>
<dataflow id="118" from="p_str" to="specinterface_ln0" fromId="31" toId="12">
</dataflow>
<dataflow id="119" from="StgValue_38" to="specinterface_ln0" fromId="38" toId="12">
</dataflow>
<dataflow id="120" from="StgValue_38" to="specinterface_ln0" fromId="38" toId="12">
</dataflow>
<dataflow id="121" from="StgValue_41" to="specinterface_ln0" fromId="41" toId="12">
</dataflow>
<dataflow id="122" from="StgValue_41" to="specinterface_ln0" fromId="41" toId="12">
</dataflow>
<dataflow id="123" from="p_str" to="specinterface_ln0" fromId="31" toId="12">
</dataflow>
<dataflow id="124" from="ScalarProp_str" to="specinterface_ln0" fromId="45" toId="12">
</dataflow>
<dataflow id="125" from="StgValue_47" to="specinterface_ln0" fromId="47" toId="12">
</dataflow>
<dataflow id="126" from="StgValue_28" to="specinterface_ln0" fromId="28" toId="12">
</dataflow>
<dataflow id="128" from="_ssdm_op_Write.ap_fifo.i64P0A" to="write_ln0" fromId="127" toId="13">
</dataflow>
<dataflow id="129" from="Output_r_c" to="write_ln0" fromId="16" toId="13">
</dataflow>
<dataflow id="130" from="Output_r_read" to="write_ln0" fromId="6" toId="13">
</dataflow>
</dataflows>


</stg>
